genenv.py
genenv-1.0.2.data/scripts/createnv.sh
genenv-1.0.2.dist-info/LICENSE
genenv-1.0.2.dist-info/METADATA
genenv-1.0.2.dist-info/WHEEL
genenv-1.0.2.dist-info/entry_points.txt
genenv-1.0.2.dist-info/top_level.txt
genenv-1.0.2.dist-info/RECORD
