Metadata-Version: 2.1
Name: genenv
Version: 1.0.2
Summary: command line utility tool that allows you to create python virtual environements with already installed dependencies you want easily
Home-page: https://github.com/Gwali-1/GENENV.git
Author: Matthew Gwalisam
Author-email: gwalisam37@email.com
License: MIT
Classifier: Development Status :: 5 - Production/Stable
Classifier: Intended Audience :: Developers
Classifier: License :: OSI Approved :: MIT License
Classifier: Programming Language :: Python :: 3.7
Classifier: Programming Language :: Python :: 3.8
Classifier: Programming Language :: Python :: 3.11
Requires-Python: >=3.7
License-File: LICENSE
Requires-Dist: click
